vaultxfer/__init__.py
vaultxfer/cli.py
vaultxfer/ssh_client.py
vaultxfer/transfer.py
vaultxfer/utils.py
vaultxfer-0.1.1.dist-info/licenses/LICENSE
vaultxfer-0.1.1.dist-info/METADATA
vaultxfer-0.1.1.dist-info/WHEEL
vaultxfer-0.1.1.dist-info/entry_points.txt
vaultxfer-0.1.1.dist-info/top_level.txt
vaultxfer-0.1.1.dist-info/RECORD
