Metadata-Version: 2.4
Name: vaultxfer
Version: 0.1.1
Summary: SSH/SFTP file transfer and synchronization CLI with atomic operations
Author-email: Bryan Charles <bryancharlesdnz@gmail.com>
License: MIT
Project-URL: Homepage, https://github.com/agace/vaultxfer
Project-URL: Documentation, https://github.com/agace/vaultxfer#readme
Project-URL: Repository, https://github.com/agace/vaultxfer
Project-URL: Issues, https://github.com/agace/vaultxfer/issues
Keywords: ssh,sftp,file-transfer,synchronization,cli
Requires-Python: >=3.10
License-File: LICENSE
Requires-Dist: paramiko<4.0,>=2.11
Dynamic: license-file
